AlmaIndicate/Alma.py
AlmaIndicate/__init__.py
AlmaIndicate-0.0.2.dist-info/LICENSE.txt
AlmaIndicate-0.0.2.dist-info/METADATA
AlmaIndicate-0.0.2.dist-info/WHEEL
AlmaIndicate-0.0.2.dist-info/top_level.txt
AlmaIndicate-0.0.2.dist-info/RECORD
