Metadata-Version: 2.1
Name: AlmaIndicate
Version: 0.0.2
Summary: A small library for computing ALMA indicator for stocks
Home-page: https://github.com/karunstha/ta-alma
Author: Mark Lester A. Bolotaolo, Karun Shrestha
Classifier: Programming Language :: Python :: 3
Classifier: License :: OSI Approved :: MIT License
Classifier: Operating System :: OS Independent
Requires-Python: >=3.6
License-File: LICENSE.txt
Requires-Dist: numpy
Requires-Dist: pandas
Requires-Dist: python-dateutil
Requires-Dist: pytz
Requires-Dist: six
Requires-Dist: ta
